codesecdirectgpl3/__init__.py
codesecdirectgpl3/module1.py
codesecdirectgpl3-0.1.0.dist-info/LICENSE
codesecdirectgpl3-0.1.0.dist-info/METADATA
codesecdirectgpl3-0.1.0.dist-info/WHEEL
codesecdirectgpl3-0.1.0.dist-info/top_level.txt
codesecdirectgpl3-0.1.0.dist-info/RECORD
