Metadata-Version: 2.1
Name: codesecdirectgpl3
Version: 0.1.0
Summary: A sample Python package
Author-email: Your Name <you@example.com>
License: GPL-3.0
Project-URL: Homepage, https://github.com/james-0131-2/pycodesecdirectgpl3
Project-URL: Repository, https://github.com/james-0131-2/pycodesecdirectgpl3
Requires-Python: >=3.7
License-File: LICENSE
Requires-Dist: requests
